<?xml version="1.0" ?>
<level author="david" bg="1" name="dontmove">
	
  
	<wall height="103" width="174" x="165" y="302"/>
	
  
	<wall height="114" width="87" x="322" y="126"/>
	
  
	<wall height="175" width="101" x="136" y="-27"/>
	
  
	<wall height="193" width="110" x="316" y="-166"/>
	
  
	<wall height="175" width="122" x="131" y="-280"/>
	
  
	<wall height="167" width="109" x="333" y="-404"/>
	
  
	<boost height="201" width="134" x="124" y="-537"/>
	
  
	<boost height="192" width="221" x="95" y="-730"/>
	
  
	<boost height="174" width="292" x="52" y="-905"/>
	
  
	<boost height="149" width="172" x="119" y="-1056"/>
	
  
	<boost height="118" width="91" x="161" y="-1177"/>
	
  
	<deathwall height="162" width="140" x="307" y="-1204"/>
	
  
	<deathwall height="183" width="81" x="20" y="-1219"/>
	
  
	<boost height="138" width="161" x="121" y="-1317"/>
	
  
	<goal height="122" width="225" x="89" y="-1441"/>
	
  
	<textfield text="that must have been hard! now you can rest" x="98" y="-150"/>
	
  
	<textfield text="dont move!!!!!!" x="57" y="-497"/>
	
  
	<textfield text="and dont say i didnt warn you!" x="330" y="-829"/>
	
  
	<textfield text="horray! you made it!" x="329" y="-1265"/>
	

</level>
