<?xml version="1.0" ?>
<level author="mellee" bg="1" name="hle">
	
  
	<wall height="52" width="253" x="50" y="268"/>
	
  
	<trackwall height="52" width="102" x="302" y="267"/>
	
  
	<track height="237" width="16" x="328" y="75"/>
	
  
	<wall height="49" width="100" x="201" y="71"/>
	
  
	<deathwall height="49" width="53" x="151" y="70"/>
	
  
	<wall height="54" width="102" x="49" y="68"/>
	
  
	<trackwall height="48" width="-47" x="46" y="71"/>
	
  
	<wall height="50" width="101" x="52" y="-181"/>
	
  
	<wall height="46" width="103" x="148" y="-229"/>
	
  
	<track height="50" width="141" x="251" y="-229"/>
	
  
	<trackwall height="18" width="83" x="251" y="-232"/>
	
  
	<goal height="170" width="43" x="415" y="-368"/>
	
  
	<textfield text="look at the big moveeig" x="245" y="79"/>
	
  
	<track height="447" width="16" x="18" y="-335"/>
	

</level>
