<?xml version="1.0" ?>
<level author="nohambob" bg="2" name="researchcorp4">
	
  
	<wall height="225.75" width="529.5999999999999" x="0.95" y="272"/>
	
  
	<wall height="128.64999999999998" width="91.7" x="72.2" y="172.05"/>
	
  
	<wall height="83.29999999999998" width="65.75" x="137.05" y="189.65"/>
	
  
	<wall height="50.900000000000006" width="51.849999999999994" x="28.7" y="221.1"/>
	
  
	<wall height="24.05000000000001" width="54.64999999999999" x="99.05" y="147.1"/>
	
  
	<wall height="30.55000000000001" width="28.69999999999999" x="148.15" y="159.1"/>
	
  
	<wall height="80.5" width="115.69999999999999" x="383.35" y="198"/>
	
  
	<wall height="36.099999999999994" width="39.799999999999955" x="342.6" y="236.85"/>
	
  
	<wall height="59.25" width="80.55000000000001" x="418.5" y="157.25"/>
	
  
	<wall height="21.299999999999983" width="31.5" x="389.8" y="180.4"/>
	
  
	<wall height="23.100000000000023" width="24.049999999999983" x="212.05" y="347.9"/>
	
  
	<wall height="12.949999999999989" width="25" x="313.9" y="392.3"/>
	
  
	<wall height="23.100000000000023" width="19.44999999999999" x="109.25" y="394.15"/>
	
  
	<wall height="183.19999999999993" width="501.84999999999997" x="1.85" y="495.85"/>
	
  
	<wall height="18.5" width="46.30000000000001" x="441.65" y="140.64999999999998"/>
	
  
	<wall height="30.55000000000001" width="65.69999999999999" x="425.95" y="239.64999999999998"/>
	
  
	<wall height="31.44999999999999" width="50" x="450" y="211"/>
	
  
	<wall height="19.399999999999977" width="56.5" x="91.65" y="166.60000000000002"/>
	
  
	<wall height="59.25" width="29.650000000000006" x="198.15" y="217.45"/>
	
  
	<wall height="28.69999999999999" width="17.55000000000001" x="225.95" y="248"/>
	
  
	<wall height="37.94999999999999" width="-40.75" x="36.1" y="245.2"/>
	
  
	<wall height="152.7" width="14.8" x="0.95" y="-126.75"/>
	
  
	<wall height="142.5" width="26.849999999999998" x="12.05" y="-128.6"/>
	
  
	<wall height="109.2" width="23.15" x="37.95" y="-121.2"/>
	
  
	<wall height="33.349999999999994" width="63.9" x="38.9" y="-128.6"/>
	
  
	<wall height="54.60000000000001" width="-37.99999999999999" x="83.35" y="-102.7"/>
	
  
	<wall height="-37.95" width="37.05" x="78.7" y="-76.75"/>
	
  
	<wall height="27.75" width="31.5" x="101.85" y="-128.6"/>
	
  
	<wall height="246.10000000000002" width="38.85000000000002" x="481.5" y="-355.8"/>
	
  
	<wall height="211.89999999999998" width="40.75" x="459.25" y="-354.9"/>
	
  
	<wall height="168.4" width="36.14999999999998" x="443.5" y="-355.8"/>
	
  
	<wall height="109.19999999999999" width="-51.849999999999966" x="441.65" y="-339.15"/>
	
  
	<wall height="77.69999999999999" width="56.5" x="426.85" y="-319.7"/>
	
  
	<wall height="40.69999999999999" width="25" x="410.2" y="-242"/>
	
  
	<wall height="23.099999999999994" width="21.30000000000001" x="431.5" y="-235.5"/>
	
  
	<wall height="31.5" width="-82.39999999999998" x="440.75" y="-353.05"/>
	
  
	<wall height="21.30000000000001" width="28.69999999999999" x="436.1" y="-347.5"/>
	
  
	<wall height="84.19999999999999" width="39.799999999999955" x="358.35" y="-331.75"/>
	
  
	<wall height="92.55000000000001" width="35.19999999999999" x="344.45" y="-353.05"/>
	
  
	<wall height="50.900000000000034" width="29.650000000000034" x="328.7" y="-330.85"/>
	
  
	<wall height="23.150000000000034" width="41.69999999999999" x="314.8" y="-349.35"/>
	
  
	<wall height="31.44999999999999" width="83.30000000000001" x="8.35" y="-148.55"/>
	
  
	<wall height="40.69999999999999" width="-48.15" x="40.75" y="-146.7"/>
	
  
	<wall height="26.849999999999994" width="44.4" x="0.95" y="-168.9"/>
	
  
	<wall height="25" width="-24.1" x="19.45" y="-184.65"/>
	
  
	<wall height="36.099999999999966" width="19.400000000000034" x="375.95" y="239.10000000000002"/>
	
  
	<wall height="161" width="14.8" x="0.95" y="-560.9"/>
	
  
	<wall height="125.79999999999995" width="18.5" x="13.9" y="-561.8"/>
	
  
	<wall height="92.5" width="14.799999999999997" x="31.5" y="-563.65"/>
	
  
	<wall height="83.30000000000001" width="16.65" x="44.45" y="-562.75"/>
	
  
	<wall height="12.049999999999955" width="64.8" x="56.5" y="-562.75"/>
	
  
	<wall height="32.35000000000002" width="32.39999999999999" x="100.95" y="-556.25"/>
	
  
	<wall height="19.449999999999932" width="36.10000000000001" x="119.45" y="-560.9"/>
	
  
	<wall height="31.449999999999932" width="27.799999999999997" x="55.55" y="-552.55"/>
	
  
	<wall height="37.90000000000009" width="34.25" x="82.4" y="-550.7"/>
	
  
	<wall height="38.85000000000002" width="40.699999999999996" x="54.65" y="-529.45"/>
	
  
	<wall height="50" width="43.55" x="74.05" y="-509.1"/>
	
  
	<wall height="58.25" width="36.10000000000001" x="110.2" y="-475.75"/>
	
  
	<wall height="27.75" width="25" x="97.2" y="-526.65"/>
	
  
	<wall height="24.050000000000068" width="24.10000000000001" x="86.1" y="-522.95"/>
	
  
	<wall height="23.150000000000034" width="33.3" x="50.95" y="-509.1"/>
	
  
	<wall height="33.30000000000001" width="25" x="91.65" y="-469.3"/>
	
  
	<wall height="23.099999999999966" width="26.849999999999994" x="125" y="-423.95"/>
	
  
	<track height="275.75" width="12.950000000000017" x="135.2" y="-130.9"/>
	
  
	<trackwall height="11.150000000000034" width="27.80000000000001" x="126.85" y="134.64999999999998"/>
	
  
	<wall height="247.05" width="-10.2" x="2.8" y="-403.25"/>
	
  
	<wall height="229.45" width="-60.199999999999996" x="2.8" y="24.44999999999999"/>
	
  
	<wall height="361.75" width="203.75000000000006" x="497.2" y="-111.55"/>
	
  
	<wall height="341.09999999999997" width="285.2" x="496.3" y="-652.9"/>
	
  
	<wall height="12.949999999999989" width="59.25" x="194.45" y="-155.14999999999998"/>
	
  
	<wall height="19.44999999999999" width="22.19999999999999" x="231.5" y="-146.8"/>
	
  
	<wall height="12" width="65.75" x="262.05" y="-271"/>
	
  
	<wall height="14.800000000000011" width="20.350000000000023" x="300.95" y="-263.6"/>
	
  
	<wall height="23.150000000000034" width="28.69999999999999" x="280.55" y="-267.3"/>
	
  
	<wall height="22.25" width="13.899999999999977" x="293.5" y="-249.7"/>
	
  
	<wall height="10.200000000000045" width="72.19999999999999" x="81.5" y="-323.85"/>
	
  
	<wall height="15.75" width="40.749999999999986" x="97.2" y="-322"/>
	
  
	<wall height="20.399999999999977" width="37.94999999999999" x="109.25" y="-313.65"/>
	
  
	<wall height="13" width="19.450000000000003" x="119.45" y="-300.7"/>
	
  
	<wall height="108.44999999999999" width="32.44999999999999" x="370.35" y="-449.2"/>
	
  
	<wall height="155.7" width="33.35000000000002" x="444.45" y="-508.5"/>
	
  
	<wall height="25" width="93.5" x="129.65" y="-577.1"/>
	
  
	<wall height="29.649999999999977" width="31.450000000000017" x="210.2" y="-555.8"/>
	
  
	<wall height="24.100000000000023" width="30.55000000000001" x="186.1" y="-559.5"/>
	
  
	<wall height="63" width="-25.900000000000034" x="374.05" y="-406.55"/>
	
  
	<wall height="298.45000000000005" width="-38.9" x="2.8" y="-856.5"/>
	
  
	<wall height="38.89999999999998" width="55.55000000000001" x="421.3" y="-544.75"/>
	
  
	<wall height="46.35000000000002" width="47.25" x="449.05" y="-577.2"/>
	
  
	<wall height="35.200000000000045" width="27.80000000000001" x="475" y="-606.85"/>
	
  
	<wall height="25.950000000000045" width="20.400000000000034" x="487.95" y="-626.35"/>
	
  
	<wall height="30.600000000000136" width="52.8" x="1.85" y="-1168.15"/>
	
  
	<wall height="74.15000000000009" width="-52.8" x="40.75" y="-1151.45"/>
	
  
	<wall height="31.5" width="95.39999999999998" x="318.5" y="-1160.7"/>
	
  
	<wall height="97.34999999999991" width="128.7" x="365.75" y="-1156.1"/>
	
  
	<wall height="124.20000000000005" width="99.05000000000001" x="412.05" y="-1159.8"/>
	
  
	<wall height="103.79999999999995" width="72.20000000000005" x="456.5" y="-1058.75"/>
	
  
	<track height="-16.649999999999977" width="184.25" x="231.5" y="-579.2"/>
	
  
	<trackwall height="22.25" width="40.75" x="284.25" y="-604.2"/>
	
  
	<boostfruit x="54.65" y="-599.55"/>
	
  
	<boostfruit x="49.05" y="-751.6"/>
	
  
	<boostfruit x="49.05" y="-901.75"/>
	
  
	<boostfruit x="49.05" y="-1054.9"/>
	
  
	<boostfruit x="125.95" y="-1108.35"/>
	
  
	<textfield text="yes im home(the end)" x="205.55" y="-1289.65"/>
	
  
	<boost height="26.84999999999991" width="307.40000000000003" x="54.65" y="-1166.35"/>
	
  
	<trackwall height="177" width="115.75" x="395.35" y="-1324.85"/>
	
  
	<activatetrackwall height="59.350000000000136" width="38" x="414.8" y="-1209.95"/>
	
  
	<activatetrackwall height="32.450000000000045" width="47.25" x="412.95" y="-1294.3"/>
	
  
	<activatetrackwall height="29.649999999999864" width="26.850000000000023" x="472.2" y="-1293.35"/>
	
  
	<activatetrackwall height="13.900000000000091" width="103.70000000000005" x="398.15" y="-1339.7"/>
	
  
	<activatetrackwall height="15.799999999999955" width="86.10000000000002" x="423.15" y="-1354.55"/>
	
  
	<activatetrackwall height="17.649999999999864" width="61.14999999999998" x="445.35" y="-1370.3"/>
	
  
	<activatetrackwall height="13.950000000000045" width="44.44999999999999" x="460.2" y="-1378.65"/>
	
  
	<activatetrackwall height="54.700000000000045" width="25" x="418.5" y="-1403.65"/>
	
  
	<goal height="27.84999999999991" width="24.05000000000001" x="381.5" y="-1184"/>
	
  
	<textfield text="my house is at the top of this montain" x="142.55" y="48.94999999999999"/>
	

</level>
